rmchars/__init__.py
rmchars/__main__.py
rmchars/actions.py
rmchars/check.py
rmchars/create.py
rmchars-0.0.5.dist-info/LICENSE
rmchars-0.0.5.dist-info/METADATA
rmchars-0.0.5.dist-info/WHEEL
rmchars-0.0.5.dist-info/entry_points.txt
rmchars-0.0.5.dist-info/top_level.txt
rmchars-0.0.5.dist-info/RECORD
