Metadata-Version: 2.1
Name: rmchars
Version: 0.0.5
Summary: Recursively remove invalid characters from path names.
Home-page: https://github.com/tslight/rmchars
Author: Toby Slight
Author-email: tobyslight@gmail.com
License: UNKNOWN
Platform: UNKNOWN
Classifier: Programming Language :: Python :: 3
Classifier: License :: OSI Approved :: ISC License (ISCL)
Classifier: Operating System :: OS Independent
Requires-Dist: yorn
